README.rst
setup.py
hermes/__init__.py
hermes/config.py
hermes/node.py
hermes/proxy.py
hermes/publisher.py
hermes/receiver.py
hermes/structs.py
hermes_zmq.egg-info/PKG-INFO
hermes_zmq.egg-info/SOURCES.txt
hermes_zmq.egg-info/dependency_links.txt
hermes_zmq.egg-info/top_level.txt